cascadio.cp312-win_amd64.pyd
cascadio-0.0.15.data/platlib/msvcp140-86d316a7830700ef4e22320ab8e4ff55.dll
cascadio-0.0.15.data/platlib/TKBO-84d50106ff65238884e8e530414316bc.dll
cascadio-0.0.15.data/platlib/TKBRep-fca98e781330098e788e5dcd01e8c2fe.dll
cascadio-0.0.15.data/platlib/TKCAF-05d8dfb2e63a9be94c537e09389bf9d8.dll
cascadio-0.0.15.data/platlib/TKCDF-4f72cc855578525e1fb6b6a56d8d2ebf.dll
cascadio-0.0.15.data/platlib/TKDE-80daabc739f687d381f98b606a860f40.dll
cascadio-0.0.15.data/platlib/TKDEGLTF-c719316c5ebda088d60b285b3b11d750.dll
cascadio-0.0.15.data/platlib/TKDEOBJ-8425ae25566218aa9f2452d339fb5fcb.dll
cascadio-0.0.15.data/platlib/TKDESTEP-58ff497e6d6147516605bd51352d6566.dll
cascadio-0.0.15.data/platlib/TKernel-2c0d28f542bf305ce507aef7e22db1b4.dll
cascadio-0.0.15.data/platlib/TKG2d-5a838e98a1a36e2aec22959eebf16e9e.dll
cascadio-0.0.15.data/platlib/TKG3d-48713aff77cbe1f858a15425b74460de.dll
cascadio-0.0.15.data/platlib/TKGeomAlgo-0f21fdd14769a8abec2a6429e84a5833.dll
cascadio-0.0.15.data/platlib/TKGeomBase-681cd6311f7ad5106d5c5d454bc30664.dll
cascadio-0.0.15.data/platlib/TKHLR-e1ed5673cb173f944ae491d8de936f20.dll
cascadio-0.0.15.data/platlib/TKLCAF-d4b8d05479cf37b51b21dcfcedfd11d1.dll
cascadio-0.0.15.data/platlib/TKMath-f4d60ff601a0c06a5e2023a27eb44d65.dll
cascadio-0.0.15.data/platlib/TKMesh-d2be58583b8b7bd8baab2015f86dfb64.dll
cascadio-0.0.15.data/platlib/TKPrim-a8e627e52940c87a47756852eb40374f.dll
cascadio-0.0.15.data/platlib/TKRWMesh-996fe629424261c4a896e05caa68b25a.dll
cascadio-0.0.15.data/platlib/TKService-2ec265d662157694e6e9879bc2493086.dll
cascadio-0.0.15.data/platlib/TKShHealing-531ad812d29709079ee3c7962a3d796a.dll
cascadio-0.0.15.data/platlib/TKTopAlgo-7c4a3709302711c4e508cb011783c753.dll
cascadio-0.0.15.data/platlib/TKV3d-500e092d040618106a5e183aaa6f8f05.dll
cascadio-0.0.15.data/platlib/TKVCAF-39a37800862da47e915ec3db60520ab3.dll
cascadio-0.0.15.data/platlib/TKXCAF-a8f031e3fe9d66ba480fd26d52ad07a7.dll
cascadio-0.0.15.dist-info/DELVEWHEEL
cascadio-0.0.15.dist-info/METADATA
cascadio-0.0.15.dist-info/RECORD
cascadio-0.0.15.dist-info/WHEEL
cascadio-0.0.15.dist-info/licenses/LICENSE/LICENSE-cascadio.md
