Metadata-Version: 2.1
Name: cascadio
Version: 0.0.15
Summary: Convert STEP files to GLB using OpenCASCADE
Keywords: graphics,STEP,GLTF
Author-Email: Michael Dawson-Haggerty <mikedh@kerfed.com>
License: The MIT License (MIT)
Classifier: Programming Language :: Python
Classifier: Programming Language :: Python :: 3.7
Classifier: Programming Language :: Python :: 3.8
Classifier: Programming Language :: Python :: 3.9
Classifier: Programming Language :: Python :: 3.10
Classifier: Programming Language :: Python :: 3.11
Classifier: Programming Language :: Python :: 3.12
Classifier: Natural Language :: English
Classifier: Topic :: Scientific/Engineering
Classifier: Topic :: Multimedia :: Graphics
Classifier: Topic :: Multimedia :: Graphics :: 3D Modeling
Project-URL: Homepage, https://github.com/trimesh/cascadio
Requires-Python: >=3.7
Provides-Extra: tests
Requires-Dist: pytest; extra == "tests"
Requires-Dist: trimesh; extra == "tests"
Requires-Dist: chardet; extra == "tests"
